odoo8_addon_shopinvader_lead-8.0.1.0.0.99.dev3-py3.8-nspkg.pth
odoo_addons/shopinvader_lead/README.rst
odoo_addons/shopinvader_lead/__init__.py
odoo_addons/shopinvader_lead/__openerp__.py
odoo_addons/shopinvader_lead/controllers/__init__.py
odoo_addons/shopinvader_lead/controllers/main.py
odoo_addons/shopinvader_lead/models/__init__.py
odoo_addons/shopinvader_lead/models/lead.py
odoo_addons/shopinvader_lead/models/notification.py
odoo_addons/shopinvader_lead/services/__init__.py
odoo_addons/shopinvader_lead/services/lead.py
odoo_addons/shopinvader_lead/tests/__init__.py
odoo_addons/shopinvader_lead/tests/test_lead.py
odoo8_addon_shopinvader_lead-8.0.1.0.0.99.dev3.dist-info/METADATA
odoo8_addon_shopinvader_lead-8.0.1.0.0.99.dev3.dist-info/WHEEL
odoo8_addon_shopinvader_lead-8.0.1.0.0.99.dev3.dist-info/namespace_packages.txt
odoo8_addon_shopinvader_lead-8.0.1.0.0.99.dev3.dist-info/top_level.txt
odoo8_addon_shopinvader_lead-8.0.1.0.0.99.dev3.dist-info/RECORD
